Metadata-Version: 2.1
Name: odoo14-addon-sale-order-product-assortment
Version: 14.0.2.0.0
Summary: Module that allows to use the assortments on sale orders
Home-page: https://github.com/OCA/sale-workflow
Author: Tecnativa, Odoo Community Association (OCA)
Author-email: support@odoo-community.org
License: AGPL-3
Platform: UNKNOWN
Classifier: Programming Language :: Python
Classifier: Framework :: Odoo
Classifier: Framework :: Odoo :: 14.0
Classifier: License :: OSI Approved :: GNU Affero General Public License v3
Classifier: Development Status :: 4 - Beta
Requires-Python: >=3.6
Requires-Dist: odoo14-addon-base-view-inheritance-extension
Requires-Dist: odoo14-addon-product-assortment
Requires-Dist: odoo <14.1dev,>=14.0a
